MANIFEST.in
setup.py
breakdown/__init__.py
breakdown/settings.py
breakdown/templatetags.py
breakdown/utils.py
breakdown.egg-info/PKG-INFO
breakdown.egg-info/SOURCES.txt
breakdown.egg-info/dependency_links.txt
breakdown.egg-info/requires.txt
breakdown.egg-info/top_level.txt
breakdown/img/sample.png
breakdown/templates/base.html
breakdown/templates/error.html
breakdown/templates/list.html
scripts/breakdown