Metadata-Version: 1.0
Name: breakdown
Version: 1.0.8
Summary: Lightweight jinja2 template prototyping server
Home-page: UNKNOWN
Author: Concentric Sky
Author-email: code@concentricsky.com
License: UNKNOWN
Platform: UNKNOWN
Classifier: Environment :: Console
Classifier: Operating System :: MacOS :: MacOS X
Classifier: Operating System :: Microsoft :: Windows
Classifier: Operating System :: POSIX :: Linux
Classifier: Programming Language :: Python
Classifier: Framework :: Django
Classifier: Topic :: Text Processing :: Markup :: HTML
